saseg_runner/ExtractCodeAndLog.vbs
saseg_runner/__init__.py
saseg_runner/runner.py
saseg_runner-0.1.14.dist-info/METADATA
saseg_runner-0.1.14.dist-info/WHEEL
saseg_runner-0.1.14.dist-info/entry_points.txt
saseg_runner-0.1.14.dist-info/top_level.txt
saseg_runner-0.1.14.dist-info/RECORD
