Metadata-Version: 2.1
Name: saseg-runner
Version: 0.1.14
Summary: python runner for SAS Enterprise Gide file
Home-page: https://github.com/kjnh10/saseg_runner
Author: kjnh10
Author-email: kojinho10@gmail.com
License: UNKNOWN
Project-URL: Bug Reports, https://github.com/kjnh10/saseg_runner/issues
Project-URL: Funding, https://donate.pypi.org
Project-URL: Source, https://github.com/kjnh10/saseg_runner
Keywords: python egp sas enterprise guide
Platform: UNKNOWN
Classifier: Development Status :: 3 - Alpha
Classifier: Intended Audience :: Developers
Classifier: Topic :: Software Development :: Build Tools
Classifier: License :: OSI Approved :: MIT License
Classifier: Programming Language :: Python :: 3.6
Classifier: Programming Language :: Python :: 3.7
Requires-Python: >=3.6
Requires-Dist: click (>=7.0)
Requires-Dist: pypiwin32 (==223)
Requires-Dist: pywin32 (>=227)
